{"name":"Actualizar datos de reserva exitosamente","id":"modificar-informacion-de-reservas;actualizar-datos-de-reserva-exitosamente","testSteps":[{"number":1,"description":"Dado que accedo al recurso web de los servicios para modificar","duration":86,"startTime":"2022-04-28T11:26:26.957582100-05:00[America/Bogota]","result":"SUCCESS","precondition":false,"level":0},{"number":2,"description":"Cuando quiero modificar alguno de los datos de mi reserva","duration":8112,"startTime":"2022-04-28T11:26:27.047645600-05:00[America/Bogota]","result":"SUCCESS","precondition":false,"level":0,"children":[{"number":3,"description":"GET https://app-restaurante-back-qa.herokuapp.com/api/reserva/ea873ed4-0","duration":1,"startTime":"2022-04-28T11:26:33.681688700-05:00[America/Bogota]","result":"SUCCESS","restQuery":{"method":"GET","path":"https://app-restaurante-back-qa.herokuapp.com/api/reserva/ea873ed4-0","content":"{\n    \"cliente\": {\n        \"apellido\": \"Witting\",\n        \"email\": \"berry.runolfsdottir@example.com\",\n        \"nombre\": \"Meg\"\n    },\n    \"dia\": \"5/23/2022\",\n    \"hora\": \"12:00\",\n    \"mensaje\": \"Lasagne Pineapple Raspberry\",\n    \"telefono\": \"9727818338\",\n    \"cantidadPersonas\": 3\n}","contentType":"application/json","requestHeaders":"Accept\u003d*/*\r\n\t\t\t\tContent-Type\u003dapplication/json","requestCookies":"","responseHeaders":"Server: Cowboy\r\nDate: Thu, 28 Apr 2022 16:26:31 GMT\r\nConnection: keep-alive\r\nVary: Origin\r\nVary: Access-Control-Request-Method\r\nVary: Access-Control-Request-Headers\r\nContent-Type: application/json\r\nContent-Length: 198\r\nVia: 1.1 vegur\r","responseCookies":"\r","responseBody":"{\n    \"id\": \"ea873ed4-0\",\n    \"mensaje\": \"bandeja paisa\",\n    \"hora\": \"12:00\",\n    \"dia\": \"4/11/2022\",\n    \"cliente\": {\n        \"nombre\": \"Sofia\",\n        \"apellido\": \"Rivera\",\n        \"email\": \"sofia@gmail.com\"\n    },\n    \"cantidadPersonas\": 2,\n    \"telefono\": \"3228991122\"\n}","statusCode":200},"precondition":false,"level":1},{"number":4,"description":"Comensal put con parametro","duration":923,"startTime":"2022-04-28T11:26:34.223073200-05:00[America/Bogota]","result":"SUCCESS","precondition":false,"level":1,"children":[{"number":5,"description":"Comensal executes a PUT on the resource /api/reserva/{id}","duration":702,"startTime":"2022-04-28T11:26:34.409206700-05:00[America/Bogota]","result":"SUCCESS","precondition":false,"level":2,"children":[{"number":6,"description":"PUT https://app-restaurante-back-qa.herokuapp.com/api/reserva/ea873ed4-0","duration":0,"startTime":"2022-04-28T11:26:35.111599200-05:00[America/Bogota]","result":"SUCCESS","restQuery":{"method":"PUT","path":"https://app-restaurante-back-qa.herokuapp.com/api/reserva/ea873ed4-0","content":"{\n    \"cliente\": {\n        \"apellido\": \"Rivera\",\n        \"email\": \"sofia@gmail.com\",\n        \"nombre\": \"Sofia\"\n    },\n    \"dia\": \"4/11/2022\",\n    \"hora\": \"12:00\",\n    \"id\": \"ea873ed4-0\",\n    \"mensaje\": \"Scotch Eggs Sprouts Chives\",\n    \"telefono\": \"3228991122\",\n    \"cantidadPersonas\": 2\n}","contentType":"application/json","requestHeaders":"Accept\u003d*/*\r\n\t\t\t\tContent-Type\u003dapplication/json; charset\u003dUTF-8","requestCookies":"","responseHeaders":"Server: Cowboy\r\nDate: Thu, 28 Apr 2022 16:26:33 GMT\r\nConnection: keep-alive\r\nVary: Origin\r\nVary: Access-Control-Request-Method\r\nVary: Access-Control-Request-Headers\r\nContent-Type: application/json\r\nContent-Length: 211\r\nVia: 1.1 vegur\r","responseCookies":"\r","responseBody":"{\n    \"id\": \"ea873ed4-0\",\n    \"mensaje\": \"Scotch Eggs Sprouts Chives\",\n    \"hora\": \"12:00\",\n    \"dia\": \"4/11/2022\",\n    \"cliente\": {\n        \"nombre\": \"Sofia\",\n        \"apellido\": \"Rivera\",\n        \"email\": \"sofia@gmail.com\"\n    },\n    \"cantidadPersonas\": 2,\n    \"telefono\": \"3228991122\"\n}","statusCode":200},"precondition":false,"level":3}]}]}]},{"number":7,"description":"Entonces obtengo como respuesta mis datos actualizados","duration":168,"startTime":"2022-04-28T11:26:35.161607800-05:00[America/Bogota]","result":"SUCCESS","precondition":false,"level":0,"children":[{"number":8,"description":"Codigo de respuesta debe ser: 200","duration":56,"startTime":"2022-04-28T11:26:35.183640500-05:00[America/Bogota]","result":"SUCCESS","precondition":false,"level":1},{"number":9,"description":"Then el dia actualizado  should be \u00274/11/2022\u0027","duration":14,"startTime":"2022-04-28T11:26:35.270685200-05:00[America/Bogota]","result":"SUCCESS","precondition":false,"level":1},{"number":10,"description":"Then la hora actualizado  should be \u002712:00\u0027","duration":12,"startTime":"2022-04-28T11:26:35.285693800-05:00[America/Bogota]","result":"SUCCESS","precondition":false,"level":1},{"number":11,"description":"Then el mensaje actualizado  should be \u0027Scotch Eggs Sprouts Chives\u0027","duration":12,"startTime":"2022-04-28T11:26:35.298704700-05:00[America/Bogota]","result":"SUCCESS","precondition":false,"level":1}]}],"userStory":{"id":"modificar-informacion-de-reservas","storyName":"Modificar informacion de reservas","displayName":"Modificar informacion de reservas","path":"reservas/ModificarReserva.feature","narrative":"  Yo como comensal\n  Quiero tener acceso al recurso de reservas\n  Para poder modificar los datos de mis reservas","type":"feature"},"featureTag":{"name":"Reservas/Modificar informacion de reservas","type":"feature","displayName":"Reservas/Modificar informacion de reservas"},"title":"Actualizar datos de reserva exitosamente","description":"","backgroundTitle":"Acceso al recurso base de la pagina","backgroundDescription":"","tags":[{"name":"Reservas","type":"capability","displayName":"Reservas"},{"name":"Reservas/Modificar informacion de reservas","type":"feature","displayName":"Modificar informacion de reservas"}],"startTime":"2022-04-28T11:26:26.938568100-05:00[America/Bogota]","duration":8393,"projectKey":"","isManualTestingUpToDate":false,"manual":false,"testSource":"Cucumber","actors":[{"name":"Comensal","can":["call an API at https://app-restaurante-back-qa.herokuapp.com"]}],"result":"SUCCESS"}